postech_pressao/__init__.py
postech_pressao/__main__.py
postech_pressao/model.py
postech_pressao/py.typed
postech_pressao-0.1.0.dist-info/METADATA
postech_pressao-0.1.0.dist-info/WHEEL
postech_pressao-0.1.0.dist-info/entry_points.txt
postech_pressao-0.1.0.dist-info/licenses/LICENSE
postech_pressao-0.1.0.dist-info/RECORD
