Metadata-Version: 2.4
Name: postech-pressao
Version: 0.1.0
Summary: Classificação simples de pressão arterial (BAIXA/NORMAL/ALTA) a partir de pares sistólica/diastólica.
Project-URL: Homepage, https://github.com/edmilsonteixeira/postech-pressao
Project-URL: Repository, https://github.com/edmilsonteixeira/postech-pressao
Project-URL: Issues, https://github.com/edmilsonteixeira/postech-pressao/issues
Author: Edmilson Teixeira
License: MIT
License-File: LICENSE
Keywords: alura,fiap,ml,pressao-arterial,pós-tech,saude,sklearn
Classifier: Intended Audience :: Developers
Classifier: License :: OSI Approved :: MIT License
Classifier: Operating System :: OS Independent
Classifier: Programming Language :: Python :: 3
Classifier: Topic :: Scientific/Engineering :: Artificial Intelligence
Requires-Python: >=3.9
Requires-Dist: numpy>=1.23
Requires-Dist: scikit-learn>=1.4
